[
  {
    "id": "th105",
    "name":
    {
      "zh-CN": "东方绯想天"
    },
    "description": {
      "zh-CN": "fxt desc"
    },
    "author": "ZUN",
    "homepage": "http://www.myacg.cc",
    "category": "ACT",
    "actions": {
      "darwin": {
        "main": {
          "execute": "",
          "args": [],
          "env": "",
          "open": ""
        }
      }
    },
    "references": {
      "id": "",
      "type": "runtime"
    },
    "locales": ["zh-CN"],
    "download": "",
    "news": [{
      "title": "title",
      "url": "",
      "image": ""
      }
    ],
    "tags": ["ACT"],
    "local": {
      "path": "",
      "version": ""
    }
  },
  {
    "id": "th12",
    "name":
    {
      "zh-CN": "地灵殿"
    },
    "description": {
      "zh-CN": "th12 desc"
    },
    "author": "ZUN",
    "homepage": "http://www.myacg.cc",
    "category": "ACT",
    "actions": {
      "darwin": {
        "main": {
          "execute": "",
          "args": [],
          "env": "",
          "open": ""
        }
      }
    },
    "references": {
      "id": "",
      "type": "runtime"
    },
    "locales": ["zh-CN"],
    "download": "",
    "news": [{
      "title": "title",
      "url": "",
      "image": ""
    }
    ],
    "tags": ["ACT"],
    "local": {
      "path": "/foo/bar",
      "version": "10.3"
    }
  }
]